ethereum_hive-0.1.0a2.dist-info/licenses/LICENSE
hive/__init__.py
hive/client.py
hive/network.py
hive/parameters.py
hive/py.typed
hive/simulation.py
hive/testing.py
hive/tests/__init__.py
hive/tests/genesis.json
hive/tests/test_sanity.py
ethereum_hive-0.1.0a2.dist-info/METADATA
ethereum_hive-0.1.0a2.dist-info/WHEEL
ethereum_hive-0.1.0a2.dist-info/top_level.txt
ethereum_hive-0.1.0a2.dist-info/RECORD
