Metadata-Version: 2.4
Name: ethereum-hive
Version: 0.1.0a2
Summary: Ethereum Hive Simulator Python API
Author-email: Mario Vega <mario.vega@ethereum.org>
Maintainer-email: Mario Vega <mario.vega@ethereum.org>, danceratopz <danceratopz@ethereum.org>
License:                     GNU GENERAL PUBLIC LICENSE
Project-URL: Homepage, https://github.com/marioevz/hive.py
Project-URL: Repository, https://github.com/marioevz/hive.py
Project-URL: Issues, https://github.com/marioevz/hive.py/issues
Project-URL: Documentation, https://github.com/marioevz/hive.py#readme
Keywords: ethereum,hive,simulator,testing,blockchain
Classifier: Development Status :: 4 - Beta
Classifier: Intended Audience :: Developers
Classifier: License :: OSI Approved :: GNU General Public License v3 (GPLv3)
Classifier: Programming Language :: Python :: 3
Classifier: Programming Language :: Python :: 3.11
Classifier: Programming Language :: Python :: 3.12
Classifier: Topic :: Software Development :: Testing
Classifier: Topic :: System :: Networking
Classifier: Topic :: Internet :: WWW/HTTP :: HTTP Servers
Classifier: Operating System :: OS Independent
Requires-Python: >=3.11
License-File: LICENSE
Requires-Dist: requests<3,>=2.31.0
Provides-Extra: test
Requires-Dist: pytest<9,>=8.4.0; extra == "test"
Requires-Dist: pytest-cov<5,>=4.1.0; extra == "test"
Provides-Extra: lint
Requires-Dist: black>=23.1.0; implementation_name == "cpython" and extra == "lint"
Requires-Dist: isort<6,>=5.8; extra == "lint"
Requires-Dist: mypy<2,>=1.4.1; extra == "lint"
Requires-Dist: types-requests<3,>=2.25.0; extra == "lint"
Provides-Extra: dev
Requires-Dist: setuptools-scm; extra == "dev"
Dynamic: license-file
